[1,0,0,[["dragonBones.DragonBonesAsset",["_name","_dragonBonesJson"],1]],[[0,0,1,3]],[[0,"wuq4_ske","{\"frameRate\":24,\"isGlobal\":0,\"name\":\"wuq4\",\"version\":\"5.0\",\"armature\":[{\"slot\":[{\"color\":{},\"name\":\"1\",\"parent\":\"1\"},{\"z\":1,\"color\":{},\"name\":\"手01\",\"parent\":\"手01\",\"displayIndex\":2},{\"z\":2,\"color\":{},\"name\":\"sm_ms_superskill1_45_hit_0001\",\"parent\":\"sm_ms_superskill1_45_hit_0001\",\"displayIndex\":9}],\"defaultActions\":[{\"gotoAndPlay\":\"攻击\"}],\"type\":\"Armature\",\"frameRate\":24,\"ik\":[],\"skin\":[{\"slot\":[{\"display\":[{\"path\":\"手01\",\"type\":\"image\",\"name\":\"手01\",\"transform\":{\"y\":-1.5167,\"skX\":33.6901,\"skY\":33.6901,\"x\":10.4846}},{\"path\":\"猫手\",\"type\":\"image\",\"name\":\"猫手\",\"transform\":{\"y\":-1.5167,\"skX\":33.6901,\"skY\":33.6901,\"x\":10.4846}},{\"path\":\"透明\",\"type\":\"image\",\"name\":\"透明\",\"transform\":{}}],\"name\":\"手01\"},{\"display\":[{\"path\":\"sm_ms_superskill1_45_hit_0001\",\"type\":\"image\",\"name\":\"sm_ms_superskill1_45_hit_0001\",\"transform\":{\"y\":8.6026,\"skX\":0.5067,\"skY\":0.5067,\"x\":96.3777}},{\"path\":\"sm_ms_superskill1_45_hit_0002\",\"type\":\"image\",\"name\":\"sm_ms_superskill1_45_hit_0002\",\"transform\":{\"y\":8.6026,\"skX\":0.5067,\"skY\":0.5067,\"x\":96.3777}},{\"path\":\"sm_ms_superskill1_45_hit_0003\",\"type\":\"image\",\"name\":\"sm_ms_superskill1_45_hit_0003\",\"transform\":{\"y\":8.6026,\"skX\":0.5067,\"skY\":0.5067,\"x\":96.3777}},{\"path\":\"sm_ms_superskill1_45_hit_0004\",\"type\":\"image\",\"name\":\"sm_ms_superskill1_45_hit_0004\",\"transform\":{\"y\":8.6026,\"skX\":0.5067,\"skY\":0.5067,\"x\":96.3777}},{\"path\":\"sm_ms_superskill1_45_hit_0005\",\"type\":\"image\",\"name\":\"sm_ms_superskill1_45_hit_0005\",\"transform\":{\"y\":8.6026,\"skX\":0.5067,\"skY\":0.5067,\"x\":96.3777}},{\"path\":\"sm_ms_superskill1_45_hit_0006\",\"type\":\"image\",\"name\":\"sm_ms_superskill1_45_hit_0006\",\"transform\":{\"y\":8.6026,\"skX\":0.5067,\"skY\":0.5067,\"x\":96.3777}},{\"path\":\"sm_ms_superskill1_45_hit_0007\",\"type\":\"image\",\"name\":\"sm_ms_superskill1_45_hit_0007\",\"transform\":{\"y\":8.6026,\"skX\":0.5067,\"skY\":0.5067,\"x\":96.3777}},{\"path\":\"sm_ms_superskill1_45_hit_0008\",\"type\":\"image\",\"name\":\"sm_ms_superskill1_45_hit_0008\",\"transform\":{\"y\":8.6026,\"skX\":0.5067,\"skY\":0.5067,\"x\":96.3777}},{\"path\":\"sm_ms_superskill1_45_hit_0009\",\"type\":\"image\",\"name\":\"sm_ms_superskill1_45_hit_0009\",\"transform\":{\"y\":8.6026,\"skX\":0.5067,\"skY\":0.5067,\"x\":96.3777}},{\"path\":\"透明\",\"type\":\"image\",\"name\":\"透明\",\"transform\":{\"y\":8.6026,\"skX\":0.5067,\"skY\":0.5067,\"x\":96.3777}}],\"name\":\"sm_ms_superskill1_45_hit_0001\"},{\"display\":[{\"path\":\"4\",\"type\":\"image\",\"name\":\"1\",\"transform\":{\"y\":3.9832,\"skX\":145.2019,\"skY\":145.2019,\"x\":47.068}}],\"name\":\"1\"}],\"name\":\"\"}],\"animation\":[{\"slot\":[{\"frame\":[{\"tweenEasing\":null,\"duration\":8}],\"name\":\"手01\"},{\"frame\":[{\"displayIndex\":9,\"duration\":1,\"tweenEasing\":null},{\"tweenEasing\":null,\"duration\":1},{\"tweenEasing\":null,\"duration\":1,\"displayIndex\":1},{\"tweenEasing\":null,\"duration\":1,\"displayIndex\":2},{\"tweenEasing\":null,\"duration\":1,\"displayIndex\":3},{\"tweenEasing\":null,\"duration\":1,\"displayIndex\":4},{\"tweenEasing\":null,\"duration\":1,\"displayIndex\":5},{\"tweenEasing\":null,\"duration\":1,\"displayIndex\":6},{\"tweenEasing\":null,\"duration\":0,\"displayIndex\":7}],\"name\":\"sm_ms_superskill1_45_hit_0001\"}],\"frame\":[],\"playTimes\":0,\"ik\":[],\"ffd\":[],\"duration\":8,\"zOrder\":{\"frame\":[{\"duration\":5,\"zOrder\":[],\"tweenEasing\":null},{\"duration\":3,\"zOrder\":[],\"tweenEasing\":null}]},\"name\":\"攻击\",\"bone\":[{\"frame\":[{\"duration\":8,\"transform\":{}}],\"name\":\"root\"},{\"frame\":[{\"duration\":2,\"transform\":{\"y\":-1.4279,\"skX\":-5.3884,\"skY\":-5.3884,\"x\":0.0167},\"tweenEasing\":0},{\"duration\":6,\"transform\":{\"y\":12.6,\"skX\":169.7031,\"skY\":169.7031,\"x\":24.0879},\"tweenEasing\":0},{\"duration\":0,\"transform\":{\"y\":12.6,\"skX\":163.2645,\"skY\":163.2645,\"x\":24.0879}}],\"name\":\"手01\"},{\"frame\":[{\"duration\":8,\"transform\":{}}],\"name\":\"1\"},{\"frame\":[{\"duration\":1,\"transform\":{}},{\"duration\":1,\"transform\":{\"y\":13.7896,\"skX\":-76.8885,\"skY\":-76.8885,\"scX\":0.7642,\"scY\":0.7642,\"x\":-13.7896},\"curve\":[0,0,0.5,1]},{\"duration\":3,\"transform\":{\"y\":13.7896,\"skX\":-11.2651,\"skY\":-11.2651,\"scX\":0.8617,\"scY\":0.8617,\"x\":3.0652}},{\"duration\":2,\"transform\":{\"y\":13.7896,\"skX\":-11.2651,\"skY\":-11.2651,\"x\":37.0083}},{\"duration\":1,\"transform\":{\"y\":13.7896,\"skX\":-11.2651,\"skY\":-11.2651,\"x\":44.6135}}],\"name\":\"sm_ms_superskill1_45_hit_0001\"}]},{\"slot\":[{\"frame\":[{\"tweenEasing\":null,\"duration\":10}],\"name\":\"手01\"}],\"frame\":[],\"playTimes\":0,\"ik\":[],\"ffd\":[],\"duration\":10,\"zOrder\":{\"frame\":[{\"duration\":10,\"zOrder\":[],\"tweenEasing\":null},{\"duration\":0,\"zOrder\":[],\"tweenEasing\":null}]},\"name\":\"走路\",\"bone\":[{\"frame\":[{\"duration\":10,\"transform\":{}}],\"name\":\"root\"},{\"frame\":[{\"duration\":10,\"transform\":{\"y\":0.75,\"skX\":-5.3884,\"skY\":-5.3884,\"x\":0.0167},\"tweenEasing\":0},{\"duration\":0,\"transform\":{\"y\":0.75,\"skX\":-5.3884,\"skY\":-5.3884,\"x\":0.0167}}],\"name\":\"手01\"},{\"frame\":[{\"duration\":10,\"transform\":{}}],\"name\":\"1\"},{\"frame\":[{\"duration\":10,\"transform\":{}}],\"name\":\"sm_ms_superskill1_45_hit_0001\"}]}],\"name\":\"Armature\",\"bone\":[{\"transform\":{},\"name\":\"root\"},{\"length\":20,\"transform\":{\"y\":-4.6,\"skX\":-49.1654,\"skY\":-49.1654,\"x\":-6.0879},\"parent\":\"root\",\"name\":\"手01\"},{\"length\":67,\"transform\":{\"y\":-10.5774,\"skX\":-0.5067,\"skY\":-0.5067,\"x\":23.8179},\"parent\":\"root\",\"name\":\"sm_ms_superskill1_45_hit_0001\"},{\"length\":96,\"transform\":{\"y\":12.052,\"skX\":-96.0365,\"skY\":-96.0365,\"x\":14.7113},\"parent\":\"手01\",\"name\":\"1\"}],\"aabb\":{\"width\":229.99547181624354,\"y\":-79.9819053032472,\"height\":127.15452435086706,\"x\":-65.22761467338647}}]}"]],0,0,[],[],[]]