[1,0,0,[["dragonBones.DragonBonesAsset",["_name","_dragonBonesJson"],1]],[[0,0,1,3]],[[0,"wuq13_ske","{\"frameRate\":24,\"isGlobal\":0,\"name\":\"wuq13\",\"version\":\"5.0\",\"armature\":[{\"slot\":[{\"color\":{},\"name\":\"1\",\"parent\":\"1\"},{\"z\":1,\"color\":{},\"name\":\"手01\",\"parent\":\"手01\",\"displayIndex\":2},{\"z\":2,\"color\":{},\"name\":\"00000\",\"parent\":\"00000\",\"displayIndex\":-1}],\"type\":\"Armature\",\"frameRate\":24,\"bone\":[{\"transform\":{},\"name\":\"root\"},{\"length\":20,\"transform\":{\"y\":-4.6,\"skX\":-49.1654,\"skY\":-49.1654,\"x\":-6.0879},\"parent\":\"root\",\"name\":\"手01\"},{\"length\":64,\"transform\":{\"y\":-16.7125,\"skX\":-1.3384,\"skY\":-1.3384,\"x\":82.8636},\"parent\":\"root\",\"name\":\"00000\"},{\"length\":96,\"transform\":{\"y\":12.052,\"skX\":-96.0365,\"skY\":-96.0365,\"x\":14.7113},\"parent\":\"手01\",\"name\":\"1\"}],\"defaultActions\":[{\"gotoAndPlay\":\"攻击\"}],\"skin\":[{\"slot\":[{\"display\":[{\"path\":\"9\",\"type\":\"image\",\"name\":\"1\",\"transform\":{\"y\":6.187,\"skX\":145.2019,\"skY\":145.2019,\"x\":51.7017}}],\"name\":\"1\"},{\"display\":[{\"path\":\"00000\",\"type\":\"image\",\"name\":\"00000\",\"transform\":{\"y\":-2.0024,\"skX\":1.3384,\"skY\":1.3384,\"x\":109.384}},{\"path\":\"00001\",\"type\":\"image\",\"name\":\"00001\",\"transform\":{\"y\":-2.0024,\"skX\":1.3384,\"skY\":1.3384,\"x\":109.384}},{\"path\":\"00002\",\"type\":\"image\",\"name\":\"00002\",\"transform\":{\"y\":-2.0024,\"skX\":1.3384,\"skY\":1.3384,\"x\":109.384}},{\"path\":\"00003\",\"type\":\"image\",\"name\":\"00003\",\"transform\":{\"y\":-2.0024,\"skX\":1.3384,\"skY\":1.3384,\"x\":109.384}},{\"path\":\"00004\",\"type\":\"image\",\"name\":\"00004\",\"transform\":{\"y\":-2.0024,\"skX\":1.3384,\"skY\":1.3384,\"x\":109.384}},{\"path\":\"00005\",\"type\":\"image\",\"name\":\"00005\",\"transform\":{\"y\":-2.0024,\"skX\":1.3384,\"skY\":1.3384,\"x\":109.384}},{\"path\":\"00006\",\"type\":\"image\",\"name\":\"00006\",\"transform\":{\"y\":-2.0024,\"skX\":1.3384,\"skY\":1.3384,\"x\":109.384}},{\"path\":\"00007\",\"type\":\"image\",\"name\":\"00007\",\"transform\":{\"y\":-2.0024,\"skX\":1.3384,\"skY\":1.3384,\"x\":109.384}},{\"path\":\"00008\",\"type\":\"image\",\"name\":\"00008\",\"transform\":{\"y\":-2.0024,\"skX\":1.3384,\"skY\":1.3384,\"x\":109.384}},{\"path\":\"00009\",\"type\":\"image\",\"name\":\"00009\",\"transform\":{\"y\":-2.0024,\"skX\":1.3384,\"skY\":1.3384,\"x\":109.384}},{\"path\":\"透明\",\"type\":\"image\",\"name\":\"透明\",\"transform\":{\"y\":-2.0024,\"skX\":1.3384,\"skY\":1.3384,\"x\":109.384}}],\"name\":\"00000\"},{\"display\":[{\"path\":\"手01\",\"type\":\"image\",\"name\":\"手01\",\"transform\":{\"y\":-1.5167,\"skX\":33.6901,\"skY\":33.6901,\"x\":10.4846}},{\"path\":\"猫手\",\"type\":\"image\",\"name\":\"手2\",\"transform\":{\"y\":-1.5167,\"skX\":33.6901,\"skY\":33.6901,\"x\":10.4846}},{\"path\":\"透明\",\"type\":\"image\",\"name\":\"透明\",\"transform\":{}}],\"name\":\"手01\"}],\"name\":\"\"}],\"animation\":[{\"slot\":[{\"frame\":[{\"tweenEasing\":null,\"duration\":8}],\"name\":\"手01\"},{\"frame\":[{\"tweenEasing\":null,\"duration\":1,\"displayIndex\":1},{\"tweenEasing\":null,\"duration\":1,\"displayIndex\":2},{\"tweenEasing\":null,\"duration\":1,\"displayIndex\":3},{\"tweenEasing\":null,\"duration\":1,\"displayIndex\":4},{\"tweenEasing\":null,\"duration\":1,\"displayIndex\":5},{\"tweenEasing\":null,\"duration\":1,\"displayIndex\":6},{\"tweenEasing\":null,\"duration\":1,\"displayIndex\":7},{\"tweenEasing\":null,\"duration\":1,\"color\":{\"aM\":35},\"displayIndex\":8},{\"tweenEasing\":0,\"duration\":0,\"color\":{\"aM\":35},\"displayIndex\":10}],\"name\":\"00000\"}],\"frame\":[],\"playTimes\":0,\"ffd\":[],\"duration\":8,\"zOrder\":{\"frame\":[{\"duration\":8,\"zOrder\":[],\"tweenEasing\":null}]},\"name\":\"攻击\",\"bone\":[{\"frame\":[{\"duration\":8,\"transform\":{}}],\"name\":\"root\"},{\"frame\":[{\"duration\":2,\"transform\":{},\"tweenEasing\":0},{\"duration\":6,\"transform\":{\"y\":22.8506,\"skX\":-189.6474,\"skY\":-189.6474,\"x\":22.6236},\"tweenEasing\":0},{\"duration\":0,\"transform\":{\"y\":22.8506,\"skX\":-197.4301,\"skY\":-197.4301,\"x\":22.6236}}],\"name\":\"手01\"},{\"frame\":[{\"duration\":8,\"transform\":{}}],\"name\":\"1\"},{\"frame\":[{\"duration\":7,\"transform\":{},\"curve\":[0,0,0,0.9857870551775727]},{\"duration\":1,\"transform\":{\"scX\":1.39,\"scY\":1.39}}],\"name\":\"00000\"}],\"ik\":[]},{\"slot\":[{\"frame\":[{\"tweenEasing\":null,\"duration\":10}],\"name\":\"手01\"}],\"frame\":[],\"playTimes\":0,\"ffd\":[],\"duration\":10,\"zOrder\":{\"frame\":[{\"duration\":10,\"zOrder\":[],\"tweenEasing\":null},{\"duration\":0,\"zOrder\":[],\"tweenEasing\":null}]},\"name\":\"走路\",\"bone\":[{\"frame\":[{\"duration\":10,\"transform\":{}}],\"name\":\"root\"},{\"frame\":[{\"duration\":10,\"transform\":{\"y\":-1.4279,\"skX\":6.6353,\"skY\":6.6353,\"x\":0.0167},\"tweenEasing\":0},{\"duration\":0,\"transform\":{\"y\":-1.4279,\"skX\":6.6353,\"skY\":6.6353,\"x\":0.0167}}],\"name\":\"手01\"},{\"frame\":[{\"duration\":10,\"transform\":{}}],\"name\":\"1\"},{\"frame\":[{\"duration\":10,\"transform\":{}}],\"name\":\"00000\"}],\"ik\":[]}],\"name\":\"Armature\",\"ik\":[],\"aabb\":{\"width\":112.68700493581039,\"y\":-90.43600437342295,\"height\":135.83600437342295,\"x\":-74.27495096268949}}]}"]],0,0,[],[],[]]