[1,["fdfxakfz1DUZj/Uno7zZ6h"],["_texture"],[["dragonBones.DragonBonesAtlasAsset",["_name","_atlasJson"],1]],[[0,0,1,3]],[[0,"CHmilin_tex","{\"imagePath\":\"CHmilin_tex.png\",\"width\":512,\"height\":1024,\"name\":\"CHmilin\",\"SubTexture\":[{\"width\":382,\"y\":1,\"height\":199,\"name\":\"高级矿工外发光\",\"x\":1},{\"width\":275,\"y\":202,\"height\":117,\"name\":\"方块世界2\",\"x\":1},{\"width\":182,\"y\":546,\"height\":36,\"name\":\"高级矿工字\",\"x\":203},{\"width\":111,\"y\":1,\"height\":151,\"name\":\"方块世界1\",\"x\":385},{\"frameY\":0,\"y\":556,\"frameWidth\":340,\"frameHeight\":155,\"width\":82,\"height\":82,\"name\":\"反光0003\",\"frameX\":-5,\"x\":1},{\"frameY\":-94,\"y\":321,\"frameWidth\":340,\"frameHeight\":155,\"width\":42,\"height\":61,\"name\":\"反光0012\",\"frameX\":-298,\"x\":234},{\"frameY\":-144,\"y\":384,\"frameWidth\":340,\"frameHeight\":155,\"width\":11,\"height\":11,\"name\":\"反光0014\",\"frameX\":-318,\"x\":250},{\"frameY\":-73,\"y\":154,\"frameWidth\":340,\"frameHeight\":155,\"width\":73,\"height\":82,\"name\":\"反光0011\",\"frameX\":-267,\"x\":430},{\"frameY\":-51,\"y\":404,\"frameWidth\":340,\"frameHeight\":155,\"width\":132,\"height\":81,\"name\":\"反光0008\",\"frameX\":-113,\"x\":234},{\"frameY\":-38,\"y\":305,\"frameWidth\":340,\"frameHeight\":155,\"width\":153,\"height\":97,\"name\":\"反光0009\",\"frameX\":-172,\"x\":278},{\"frameY\":-135,\"y\":154,\"frameWidth\":340,\"frameHeight\":155,\"width\":23,\"height\":20,\"name\":\"反光0013\",\"frameX\":-306,\"x\":385},{\"frameY\":-51,\"y\":202,\"frameWidth\":340,\"frameHeight\":155,\"width\":150,\"height\":101,\"name\":\"反光0007\",\"frameX\":-41,\"x\":278},{\"frameY\":-38,\"y\":447,\"frameWidth\":340,\"frameHeight\":155,\"width\":108,\"height\":97,\"name\":\"反光0010\",\"frameX\":-230,\"x\":101},{\"frameY\":-25,\"y\":321,\"frameWidth\":340,\"frameHeight\":155,\"width\":121,\"height\":121,\"name\":\"反光0006\",\"frameX\":-7,\"x\":1},{\"frameY\":0,\"y\":321,\"frameWidth\":340,\"frameHeight\":155,\"width\":108,\"height\":124,\"name\":\"反光0005\",\"frameX\":0,\"x\":124},{\"frameY\":-46,\"y\":384,\"frameWidth\":340,\"frameHeight\":155,\"width\":14,\"height\":14,\"name\":\"反光0002\",\"frameX\":-13,\"x\":234},{\"frameY\":0,\"y\":444,\"frameWidth\":340,\"frameHeight\":155,\"width\":98,\"height\":110,\"name\":\"反光0004\",\"frameX\":0,\"x\":1},{\"frameY\":-8,\"y\":546,\"frameWidth\":100,\"frameHeight\":100,\"width\":100,\"height\":83,\"name\":\"闪光\",\"frameX\":0,\"x\":101}]}"]],0,0,[0],[0],[0]]